cutde/.rendered.double.cpp_backend.cpp
cutde/.rendered.float.cpp_backend.cpp
cutde/TDdispFS.py
cutde/__init__.py
cutde/aca.cu
cutde/aca.py
cutde/backend.py
cutde/blocks.cu
cutde/common.cu
cutde/coordinators.py
cutde/cpp.py
cutde/cpp_backend.cpp
cutde/cpp_backend_double.cp39-win32.pyd
cutde/cpp_backend_float.cp39-win32.pyd
cutde/cuda.py
cutde/free.cu
cutde/fullspace.py
cutde/geometry.py
cutde/gpu_backend.py
cutde/halfspace.py
cutde/matrix.cu
cutde/opencl.py
cutde/pairs.cu
cutde-25.7.24.dist-info/licenses/LICENSE
cutde-25.7.24.dist-info/METADATA
cutde-25.7.24.dist-info/WHEEL
cutde-25.7.24.dist-info/top_level.txt
cutde-25.7.24.dist-info/RECORD
