Metadata-Version: 2.4
Name: cutde
Version: 25.7.24
Summary: 130 million TDEs per second, Python + CUDA TDEs from Nikkhoo and Walter 2015
Author-email: "T. Ben Thompson" <t.ben.thompson@gmail.com>
License: MIT
Project-URL: Homepage, https://github.com/tbenthompson/cutde
Project-URL: Repository, https://github.com/tbenthompson/cutde
Classifier: License :: OSI Approved :: MIT License
Classifier: Programming Language :: Python :: 3
Classifier: Operating System :: OS Independent
Requires-Python: >=3.8
License-File: LICENSE
Requires-Dist: mako
Requires-Dist: numpy
Dynamic: license-file
